pandemic_models/__init__.py
pandemic_models/models/__init__.py
pandemic_models/models/base.py
pandemic_models/models/seir_model.py
pandemic_models/models/sir_model.py
pandemic_models/models/sird_model.py
pandemic_models/optimizers/__init__.py
pandemic_models/optimizers/base.py
pandemic_models/optimizers/core.py
pandemic_models/optimizers/objective_functions.py
pandemic_models/trainer/__init__.py
pandemic_models/trainer/trainer.py
pandemic_models-0.1.2.dist-info/METADATA
pandemic_models-0.1.2.dist-info/WHEEL
pandemic_models-0.1.2.dist-info/RECORD
